jedis/__init__.py
jedis/jedis.py
jedis-0.1.1.dist-info/LICENSE
jedis-0.1.1.dist-info/METADATA
jedis-0.1.1.dist-info/WHEEL
jedis-0.1.1.dist-info/top_level.txt
jedis-0.1.1.dist-info/RECORD
