Metadata-Version: 2.1
Name: jedis
Version: 0.1.1
Summary: An easy way to manage data in json
Home-page: https://github.com/Kobsser/Jedis
Author: Kobsser
Author-email: devmoein@gmail.com
License: MIT
Keywords: json python redis jedis PyJedis Kobsser easy-json easy simple easy-json-manipulation manager
Classifier: Development Status :: 5 - Production/Stable
Classifier: Intended Audience :: Education
Classifier: Operating System :: POSIX :: Linux
Classifier: License :: OSI Approved :: MIT License
Classifier: Programming Language :: Python :: 3
License-File: LICENSE
